{
    "@context": "http://localhost:8882/d_omekas/toyo/api-context",
    "@id": "http://localhost:8882/d_omekas/toyo/api/media/15022",
    "@type": "o:Media",
    "data": [],
    "o:created": {
        "@type": "http://www.w3.org/2001/XMLSchema#dateTime",
        "@value": "2018-05-08T04:20:55+00:00"
    },
    "o:filename": "10829/P-III-a-0139_0008.jpg",
    "o:id": 15022,
    "o:ingester": "url",
    "o:is_public": true,
    "o:item": {
        "@id": "http://localhost:8882/d_omekas/toyo/api/items/10829",
        "o:id": 10829
    },
    "o:lang": null,
    "o:media_type": "image/jpeg",
    "o:modified": {
        "@type": "http://www.w3.org/2001/XMLSchema#dateTime",
        "@value": "2018-05-08T04:20:55+00:00"
    },
    "o:original_url": "http://localhost:8882/d_omekas/toyo/files/original/10829/P-III-a-0139_0008.jpg",
    "o:owner": {
        "@id": "http://localhost:8882/d_omekas/toyo/api/users/1",
        "o:id": 1
    },
    "o:renderer": "file",
    "o:resource_class": null,
    "o:resource_template": null,
    "o:sha256": "bbc1e5113521a4ff58d06b014249b9c81995e7865e84694c95d9e5672eee1e12",
    "o:size": null,
    "o:source": "http://124.33.215.236/morisonp2015/01Geography_01/P-III-a-0139_0008.jpg",
    "o:thumbnail": null,
    "o:thumbnail_urls": {
        "large": "http://localhost:8882/d_omekas/toyo/files/large/10829/P-III-a-0139_0008.jpg",
        "medium": "http://localhost:8882/d_omekas/toyo/files/medium/10829/P-III-a-0139_0008.jpg",
        "square": "http://localhost:8882/d_omekas/toyo/files/square/10829/P-III-a-0139_0008.jpg"
    },
    "o:title": null
}