{
    "@context": "http://localhost:8882/d_omekas/toyo/api-context",
    "@id": "http://localhost:8882/d_omekas/toyo/api/media/16288",
    "@type": "o:Media",
    "data": [],
    "o:created": {
        "@type": "http://www.w3.org/2001/XMLSchema#dateTime",
        "@value": "2018-05-08T04:53:32+00:00"
    },
    "o:filename": "10902/P-III-a-0241_0027.jpg",
    "o:id": 16288,
    "o:ingester": "url",
    "o:is_public": true,
    "o:item": {
        "@id": "http://localhost:8882/d_omekas/toyo/api/items/10902",
        "o:id": 10902
    },
    "o:lang": null,
    "o:media_type": "image/jpeg",
    "o:modified": {
        "@type": "http://www.w3.org/2001/XMLSchema#dateTime",
        "@value": "2018-05-08T04:53:32+00:00"
    },
    "o:original_url": "http://localhost:8882/d_omekas/toyo/files/original/10902/P-III-a-0241_0027.jpg",
    "o:owner": {
        "@id": "http://localhost:8882/d_omekas/toyo/api/users/1",
        "o:id": 1
    },
    "o:renderer": "file",
    "o:resource_class": null,
    "o:resource_template": null,
    "o:sha256": "41e08a100d86ad5c0a2115afd9c7e69030470f5882cf6f93bf537a0fd8c475e8",
    "o:size": null,
    "o:source": "http://124.33.215.236/morisonp2015/01Geography_01/P-III-a-0241_0027.jpg",
    "o:thumbnail": null,
    "o:thumbnail_urls": {
        "large": "http://localhost:8882/d_omekas/toyo/files/large/10902/P-III-a-0241_0027.jpg",
        "medium": "http://localhost:8882/d_omekas/toyo/files/medium/10902/P-III-a-0241_0027.jpg",
        "square": "http://localhost:8882/d_omekas/toyo/files/square/10902/P-III-a-0241_0027.jpg"
    },
    "o:title": null
}