{
    "@context": "http://localhost:8882/d_omekas/toyo/api-context",
    "@id": "http://localhost:8882/d_omekas/toyo/api/media/17587",
    "@type": "o:Media",
    "data": [],
    "o:created": {
        "@type": "http://www.w3.org/2001/XMLSchema#dateTime",
        "@value": "2018-05-08T05:26:57+00:00"
    },
    "o:filename": "10975/P-III-a-0289_0025.jpg",
    "o:id": 17587,
    "o:ingester": "url",
    "o:is_public": true,
    "o:item": {
        "@id": "http://localhost:8882/d_omekas/toyo/api/items/10975",
        "o:id": 10975
    },
    "o:lang": null,
    "o:media_type": "image/jpeg",
    "o:modified": {
        "@type": "http://www.w3.org/2001/XMLSchema#dateTime",
        "@value": "2018-05-08T05:26:57+00:00"
    },
    "o:original_url": "http://localhost:8882/d_omekas/toyo/files/original/10975/P-III-a-0289_0025.jpg",
    "o:owner": {
        "@id": "http://localhost:8882/d_omekas/toyo/api/users/1",
        "o:id": 1
    },
    "o:renderer": "file",
    "o:resource_class": null,
    "o:resource_template": null,
    "o:sha256": "7913c5da76ed0f7bd9f7e9495c966d8fdac7f4ab55296fc036759a6342dd86b2",
    "o:size": null,
    "o:source": "http://124.33.215.236/morisonp2015/01Geography_01/P-III-a-0289_0025.jpg",
    "o:thumbnail": null,
    "o:thumbnail_urls": {
        "large": "http://localhost:8882/d_omekas/toyo/files/large/10975/P-III-a-0289_0025.jpg",
        "medium": "http://localhost:8882/d_omekas/toyo/files/medium/10975/P-III-a-0289_0025.jpg",
        "square": "http://localhost:8882/d_omekas/toyo/files/square/10975/P-III-a-0289_0025.jpg"
    },
    "o:title": null
}