{
    "@context": "http://localhost:8882/d_omekas/toyo/api-context",
    "@id": "http://localhost:8882/d_omekas/toyo/api/media/22135",
    "@type": "o:Media",
    "data": [],
    "o:created": {
        "@type": "http://www.w3.org/2001/XMLSchema#dateTime",
        "@value": "2018-05-08T07:46:26+00:00"
    },
    "o:filename": "11252/P-III-b-0570_005.jpg",
    "o:id": 22135,
    "o:ingester": "url",
    "o:is_public": true,
    "o:item": {
        "@id": "http://localhost:8882/d_omekas/toyo/api/items/11252",
        "o:id": 11252
    },
    "o:lang": null,
    "o:media_type": "image/jpeg",
    "o:modified": {
        "@type": "http://www.w3.org/2001/XMLSchema#dateTime",
        "@value": "2018-05-08T07:46:26+00:00"
    },
    "o:original_url": "http://localhost:8882/d_omekas/toyo/files/original/11252/P-III-b-0570_005.jpg",
    "o:owner": {
        "@id": "http://localhost:8882/d_omekas/toyo/api/users/1",
        "o:id": 1
    },
    "o:renderer": "file",
    "o:resource_class": null,
    "o:resource_template": null,
    "o:sha256": "74e2815ad8ef30995d4d84b2da5b0eb5a695ed03b2e54ca58fb60c8d4d72d7d4",
    "o:size": null,
    "o:source": "http://124.33.215.236/morisonp2015/openimage/P-III-b-0570_005.jpg",
    "o:thumbnail": null,
    "o:thumbnail_urls": {
        "large": "http://localhost:8882/d_omekas/toyo/files/large/11252/P-III-b-0570_005.jpg",
        "medium": "http://localhost:8882/d_omekas/toyo/files/medium/11252/P-III-b-0570_005.jpg",
        "square": "http://localhost:8882/d_omekas/toyo/files/square/11252/P-III-b-0570_005.jpg"
    },
    "o:title": null
}