{
    "@context": "https://dch.iii.u-tokyo.ac.jp/api-context",
    "@id": "https://dch.iii.u-tokyo.ac.jp/api/media/30007",
    "@type": "o:Media",
    "data": {
        "dimensions": {
            "large": {
                "height": 800,
                "width": 507
            },
            "medium": {
                "height": 200,
                "width": 127
            },
            "original": {
                "height": 1000,
                "width": 634
            },
            "square": {
                "height": 200,
                "width": 200
            }
        }
    },
    "o:created": {
        "@type": "http://www.w3.org/2001/XMLSchema#dateTime",
        "@value": "2018-06-08T07:13:59+00:00"
    },
    "o:filename": "21427/1332747952294.jpg",
    "o:id": 30007,
    "o:ingester": "url",
    "o:is_public": true,
    "o:item": {
        "@id": "https://dch.iii.u-tokyo.ac.jp/api/items/21427",
        "o:id": 21427
    },
    "o:lang": null,
    "o:media_type": "image/jpeg",
    "o:modified": {
        "@type": "http://www.w3.org/2001/XMLSchema#dateTime",
        "@value": "2018-06-08T07:13:59+00:00"
    },
    "o:original_url": "https://dch.iii.u-tokyo.ac.jp/files/original/21427/1332747952294.jpg",
    "o:owner": {
        "@id": "https://dch.iii.u-tokyo.ac.jp/api/users/1",
        "o:id": 1
    },
    "o:renderer": "file",
    "o:resource_class": null,
    "o:resource_template": null,
    "o:sha256": "da4602c4f9097b4dda7f85428e53284cb88850a91b4450a641aab302117c9984",
    "o:size": null,
    "o:source": "http://webpark5032.sakura.ne.jp/images/large/1332747952294.jpg",
    "o:thumbnail": null,
    "o:thumbnail_urls": {
        "large": "https://dch.iii.u-tokyo.ac.jp/files/large/21427/1332747952294.jpg",
        "medium": "https://dch.iii.u-tokyo.ac.jp/files/medium/21427/1332747952294.jpg",
        "square": "https://dch.iii.u-tokyo.ac.jp/files/square/21427/1332747952294.jpg"
    },
    "o:title": null,
    "thumbnail_display_urls": {
        "large": "https://dch.iii.u-tokyo.ac.jp/files/large/21427/1332747952294.jpg",
        "medium": "https://dch.iii.u-tokyo.ac.jp/files/medium/21427/1332747952294.jpg",
        "square": "https://dch.iii.u-tokyo.ac.jp/files/square/21427/1332747952294.jpg"
    }
}