{
    "@context": "https://dch.iii.u-tokyo.ac.jp/api-context",
    "@id": "https://dch.iii.u-tokyo.ac.jp/api/media/6236",
    "@type": "o:Media",
    "data": {
        "dimensions": {
            "large": {
                "height": 800,
                "width": 534
            },
            "medium": {
                "height": 200,
                "width": 133
            },
            "original": {
                "height": 7360,
                "width": 4912
            },
            "square": {
                "height": 200,
                "width": 200
            }
        }
    },
    "dcterms:title": [
        {
            "@value": "1面",
            "is_public": true,
            "property_id": 1,
            "property_label": "Title",
            "type": "literal"
        }
    ],
    "o:created": {
        "@type": "http://www.w3.org/2001/XMLSchema#dateTime",
        "@value": "2018-05-26T15:55:15+00:00"
    },
    "o:filename": "2148/shimbunnonihon3_0398.jpg",
    "o:id": 6236,
    "o:ingester": "url",
    "o:is_public": true,
    "o:item": {
        "@id": "https://dch.iii.u-tokyo.ac.jp/api/items/2148",
        "o:id": 2148
    },
    "o:lang": null,
    "o:media_type": "image/jpeg",
    "o:modified": {
        "@type": "http://www.w3.org/2001/XMLSchema#dateTime",
        "@value": "2018-05-26T15:55:15+00:00"
    },
    "o:original_url": "https://dch.iii.u-tokyo.ac.jp/files/original/2148/shimbunnonihon3_0398.jpg",
    "o:owner": {
        "@id": "https://dch.iii.u-tokyo.ac.jp/api/users/1",
        "o:id": 1
    },
    "o:renderer": "file",
    "o:resource_class": null,
    "o:resource_template": null,
    "o:sha256": "4a5bd3f0ccd28eb8b43c278ea351433606d9c3515027ab0aa27b2a4c19078279",
    "o:size": null,
    "o:source": "https://webpark5032.sakura.ne.jp/tmp/SN/shimbunnonihon3_0398.jpg",
    "o:thumbnail": null,
    "o:thumbnail_urls": {
        "large": "https://dch.iii.u-tokyo.ac.jp/files/large/2148/shimbunnonihon3_0398.jpg",
        "medium": "https://dch.iii.u-tokyo.ac.jp/files/medium/2148/shimbunnonihon3_0398.jpg",
        "square": "https://dch.iii.u-tokyo.ac.jp/files/square/2148/shimbunnonihon3_0398.jpg"
    },
    "o:title": "1面",
    "thumbnail_display_urls": {
        "large": "https://dch.iii.u-tokyo.ac.jp/files/large/2148/shimbunnonihon3_0398.jpg",
        "medium": "https://dch.iii.u-tokyo.ac.jp/files/medium/2148/shimbunnonihon3_0398.jpg",
        "square": "https://dch.iii.u-tokyo.ac.jp/files/square/2148/shimbunnonihon3_0398.jpg"
    }
}