{
    "@context": "http://localhost:8882/d_omekas/toyo/api-context",
    "@id": "http://localhost:8882/d_omekas/toyo/api/items/11727",
    "@type": [
        "o:Item",
        "dctype:Image"
    ],
    "dcndl:callNumber": [
        {
            "@value": "P-III-a-824",
            "is_public": true,
            "property_id": 259,
            "property_label": "Call Number",
            "type": "literal"
        }
    ],
    "dcterms:identifier": [
        {
            "@value": "f0daf10b-c5f3-4655-9d79-e700cf247544",
            "is_public": true,
            "property_id": 10,
            "property_label": "Identifier",
            "type": "literal"
        }
    ],
    "dcterms:isPartOf": [
        {
            "@value": "http://124.33.215.236/morisonp2015/morisonpocr2988.php",
            "is_public": true,
            "property_id": 33,
            "property_label": "Is Part Of",
            "type": "literal"
        }
    ],
    "dcterms:publisher": [
        {
            "@value": "モリソンパンフレット画像データベース",
            "is_public": true,
            "property_id": 5,
            "property_label": "Publisher",
            "type": "literal"
        }
    ],
    "dcterms:rights": [
        {
            "@id": "http://creativecommons.org/licenses/by-nc-sa/4.0/",
            "is_public": true,
            "property_id": 15,
            "property_label": "Rights",
            "type": "uri"
        }
    ],
    "dcterms:spatial": [
        {
            "@id": "http://dbpedia.org/resource/Paris",
            "is_public": true,
            "property_id": 40,
            "property_label": "Spatial Coverage",
            "type": "uri"
        }
    ],
    "dcterms:title": [
        {
            "@value": "Notre politique en Chine.Luzeux, gén.",
            "is_public": true,
            "property_id": 1,
            "property_label": "Title",
            "type": "literal"
        }
    ],
    "ex:format": [
        {
            "@value": "52 p. ; 19 cm.",
            "is_public": true,
            "property_id": 304,
            "property_label": "形態的記述",
            "type": "literal"
        }
    ],
    "ex:heading1": [
        {
            "@value": "Luzeux, gén.",
            "is_public": true,
            "property_id": 305,
            "property_label": "heading1",
            "type": "literal"
        }
    ],
    "ex:holding": [
        {
            "@value": "（記録なし）",
            "is_public": true,
            "property_id": 306,
            "property_label": "所蔵",
            "type": "literal"
        }
    ],
    "ex:publication": [
        {
            "@value": "Paris, 1900.",
            "is_public": true,
            "property_id": 303,
            "property_label": "出版事項",
            "type": "literal"
        }
    ],
    "ex:references": [
        {
            "@id": "http://124.33.215.236/morisonp2015/morisonpocr2016_imgdir.php?tg1=III&tg2=7&tg3=F&tg4=g&tg5=",
            "is_public": true,
            "property_id": 298,
            "property_label": "引用元",
            "type": "uri"
        }
    ],
    "ex:tag1": [
        {
            "@value": "III. CHINA",
            "is_public": true,
            "property_id": 296,
            "property_label": "分類1",
            "type": "literal"
        }
    ],
    "ex:tag2": [
        {
            "@value": "7. History",
            "is_public": true,
            "property_id": 300,
            "property_label": "分類2",
            "type": "literal"
        }
    ],
    "ex:tag3": [
        {
            "@value": "F. Foreign relations",
            "is_public": true,
            "property_id": 301,
            "property_label": "分類3",
            "type": "literal"
        }
    ],
    "ex:tag4": [
        {
            "@value": "g. France",
            "is_public": true,
            "property_id": 299,
            "property_label": "分類4",
            "type": "literal"
        }
    ],
    "ex:title": [
        {
            "@value": "Notre politique en Chine.",
            "is_public": true,
            "property_id": 302,
            "property_label": "タイトル責任表示",
            "type": "literal"
        }
    ],
    "o:created": {
        "@type": "http://www.w3.org/2001/XMLSchema#dateTime",
        "@value": "2018-05-08T03:42:03+00:00"
    },
    "o:id": 11727,
    "o:is_public": true,
    "o:item_set": [
        {
            "@id": "http://localhost:8882/d_omekas/toyo/api/item_sets/1",
            "o:id": 1
        }
    ],
    "o:media": [
        {
            "@id": "http://localhost:8882/d_omekas/toyo/api/media/29161",
            "o:id": 29161
        },
        {
            "@id": "http://localhost:8882/d_omekas/toyo/api/media/29162",
            "o:id": 29162
        },
        {
            "@id": "http://localhost:8882/d_omekas/toyo/api/media/29163",
            "o:id": 29163
        },
        {
            "@id": "http://localhost:8882/d_omekas/toyo/api/media/29164",
            "o:id": 29164
        },
        {
            "@id": "http://localhost:8882/d_omekas/toyo/api/media/29165",
            "o:id": 29165
        },
        {
            "@id": "http://localhost:8882/d_omekas/toyo/api/media/29166",
            "o:id": 29166
        },
        {
            "@id": "http://localhost:8882/d_omekas/toyo/api/media/29167",
            "o:id": 29167
        },
        {
            "@id": "http://localhost:8882/d_omekas/toyo/api/media/29168",
            "o:id": 29168
        },
        {
            "@id": "http://localhost:8882/d_omekas/toyo/api/media/29169",
            "o:id": 29169
        },
        {
            "@id": "http://localhost:8882/d_omekas/toyo/api/media/29170",
            "o:id": 29170
        },
        {
            "@id": "http://localhost:8882/d_omekas/toyo/api/media/29171",
            "o:id": 29171
        },
        {
            "@id": "http://localhost:8882/d_omekas/toyo/api/media/29172",
            "o:id": 29172
        },
        {
            "@id": "http://localhost:8882/d_omekas/toyo/api/media/29173",
            "o:id": 29173
        },
        {
            "@id": "http://localhost:8882/d_omekas/toyo/api/media/29174",
            "o:id": 29174
        },
        {
            "@id": "http://localhost:8882/d_omekas/toyo/api/media/29175",
            "o:id": 29175
        },
        {
            "@id": "http://localhost:8882/d_omekas/toyo/api/media/29176",
            "o:id": 29176
        },
        {
            "@id": "http://localhost:8882/d_omekas/toyo/api/media/29177",
            "o:id": 29177
        },
        {
            "@id": "http://localhost:8882/d_omekas/toyo/api/media/29178",
            "o:id": 29178
        },
        {
            "@id": "http://localhost:8882/d_omekas/toyo/api/media/29179",
            "o:id": 29179
        },
        {
            "@id": "http://localhost:8882/d_omekas/toyo/api/media/29180",
            "o:id": 29180
        },
        {
            "@id": "http://localhost:8882/d_omekas/toyo/api/media/29181",
            "o:id": 29181
        },
        {
            "@id": "http://localhost:8882/d_omekas/toyo/api/media/29182",
            "o:id": 29182
        },
        {
            "@id": "http://localhost:8882/d_omekas/toyo/api/media/29183",
            "o:id": 29183
        },
        {
            "@id": "http://localhost:8882/d_omekas/toyo/api/media/29184",
            "o:id": 29184
        },
        {
            "@id": "http://localhost:8882/d_omekas/toyo/api/media/29185",
            "o:id": 29185
        },
        {
            "@id": "http://localhost:8882/d_omekas/toyo/api/media/29186",
            "o:id": 29186
        },
        {
            "@id": "http://localhost:8882/d_omekas/toyo/api/media/29187",
            "o:id": 29187
        },
        {
            "@id": "http://localhost:8882/d_omekas/toyo/api/media/29188",
            "o:id": 29188
        },
        {
            "@id": "http://localhost:8882/d_omekas/toyo/api/media/29189",
            "o:id": 29189
        }
    ],
    "o:modified": {
        "@type": "http://www.w3.org/2001/XMLSchema#dateTime",
        "@value": "2018-05-12T14:08:51+00:00"
    },
    "o:owner": {
        "@id": "http://localhost:8882/d_omekas/toyo/api/users/1",
        "o:id": 1
    },
    "o:resource_class": {
        "@id": "http://localhost:8882/d_omekas/toyo/api/resource_classes/26",
        "o:id": 26
    },
    "o:resource_template": {
        "@id": "http://localhost:8882/d_omekas/toyo/api/resource_templates/2",
        "o:id": 2
    },
    "o:site": [],
    "o:thumbnail": null,
    "o:title": "Notre politique en Chine.Luzeux, gén.",
    "sc:attributionLabel": [
        {
            "@value": "東洋文庫 / Toyo Bunko",
            "is_public": true,
            "property_id": 201,
            "property_label": "attributionLabel",
            "type": "literal"
        }
    ]
}